bratutils/__init__.py
bratutils/agreement.py
bratutils/bratdata.py
bratutils/redactor.py
bratutils/utils.py
bratutils-0.2.2.dist-info/LICENCE
bratutils-0.2.2.dist-info/METADATA
bratutils-0.2.2.dist-info/WHEEL
bratutils-0.2.2.dist-info/top_level.txt
bratutils-0.2.2.dist-info/zip-safe
bratutils-0.2.2.dist-info/RECORD
